formdt/__init__.py
formdt/cli.py
formdt/config.py
formdt/formatter.py
formdt/notebook.py
formdt-0.6.0.dist-info/METADATA
formdt-0.6.0.dist-info/WHEEL
formdt-0.6.0.dist-info/entry_points.txt
formdt-0.6.0.dist-info/top_level.txt
formdt-0.6.0.dist-info/RECORD
