Metadata-Version: 2.4
Name: formdt
Version: 0.6.0
Summary: An opinionated markdown formatter
Project-URL: Repository, https://github.com/sanchitram1/formdt.git
Requires-Python: >=3.13
